qlik_sense_mcp_server/__init__.py
qlik_sense_mcp_server/config.py
qlik_sense_mcp_server/engine_api.py
qlik_sense_mcp_server/repository_api.py
qlik_sense_mcp_server/server.py
qlik_sense_mcp_server/utils.py
qlik_sense_mcp_server-1.3.4.dist-info/METADATA
qlik_sense_mcp_server-1.3.4.dist-info/WHEEL
qlik_sense_mcp_server-1.3.4.dist-info/entry_points.txt
qlik_sense_mcp_server-1.3.4.dist-info/licenses/LICENSE
qlik_sense_mcp_server-1.3.4.dist-info/RECORD
