Metadata-Version: 2.4
Name: qlik-sense-mcp-server
Version: 1.3.4
Summary: MCP Server for Qlik Sense Enterprise APIs
Project-URL: Homepage, https://github.com/bintocher/qlik-sense-mcp
Project-URL: Repository, https://github.com/bintocher/qlik-sense-mcp
Project-URL: Issues, https://github.com/bintocher/qlik-sense-mcp/issues
Author-email: Stanislav Chernov <bintocher@yandex.com>
License: MIT
License-File: LICENSE
Keywords: analytics,mcp,model-context-protocol,qlik,qlik-sense
Classifier: Development Status :: 4 - Beta
Classifier: Intended Audience :: Developers
Classifier: License :: OSI Approved :: MIT License
Classifier: Programming Language :: Python :: 3
Classifier: Programming Language :: Python :: 3.12
Classifier: Topic :: Scientific/Engineering :: Information Analysis
Classifier: Topic :: Software Development :: Libraries :: Python Modules
Requires-Python: >=3.12
Requires-Dist: httpx>=0.25.0
Requires-Dist: mcp>=1.1.0
Requires-Dist: pydantic>=2.0.0
Requires-Dist: python-dotenv>=1.0.0
Requires-Dist: requests>=2.31.0
Requires-Dist: websocket-client>=1.6.0
Provides-Extra: dev
Requires-Dist: build>=0.10.0; extra == 'dev'
Requires-Dist: bump2version>=1.0.0; extra == 'dev'
Requires-Dist: twine>=4.0.0; extra == 'dev'
